novelai/__init__.py
novelai/__main__.py
novelai/client.py
novelai/constant.py
novelai/exceptions.py
novelai/utils.py
novelai/types/__init__.py
novelai/types/hostinstance.py
novelai/types/image.py
novelai/types/metadata.py
novelai/types/user.py
novelai-1.3.0.dist-info/LICENSE
novelai-1.3.0.dist-info/METADATA
novelai-1.3.0.dist-info/WHEEL
novelai-1.3.0.dist-info/top_level.txt
novelai-1.3.0.dist-info/RECORD
