Metadata-Version: 2.1
Name: novelai
Version: 1.3.0
Summary: 🎨 A lightweight async Python API for NovelAI image generation
Author: UZQueen
License: GNU AFFERO GENERAL PUBLIC LICENSE
Project-URL: Repository, https://github.com/HanaokaYuzu/NovelAI-API
Project-URL: Issues, https://github.com/HanaokaYuzu/NovelAI-API/issues
Keywords: API,async,NovelAI,AI,image generation
Classifier: Development Status :: 4 - Beta
Classifier: Intended Audience :: Developers
Classifier: Programming Language :: Python :: 3
Classifier: Programming Language :: Python :: 3.11
Classifier: Programming Language :: Python :: 3.12
Requires-Python: >=3.12
License-File: LICENSE
Requires-Dist: httpx >=0.25.2
Requires-Dist: pydantic >=2.5.3
Requires-Dist: loguru >=0.7.2
Requires-Dist: argon2-cffi >=21.3.0
